dispozitsi/__about__.py
dispozitsi/__init__.py
dispozitsi/app.py
dispozitsi/entry_points.py
dispozitsi/errors.py
dispozitsi/pattern_file_handler.py
dispozitsi/pattern_handler.py
dispozitsi/reactives.py
dispozitsi/styles.tcss
dispozitsi/patterns/grok-patterns
dispozitsi-0.1.2.dist-info/METADATA
dispozitsi-0.1.2.dist-info/WHEEL
dispozitsi-0.1.2.dist-info/entry_points.txt
dispozitsi-0.1.2.dist-info/licenses/LICENSE
dispozitsi-0.1.2.dist-info/RECORD
