Metadata-Version: 2.4
Name: dispozitsi
Version: 0.1.2
Summary: Debugger tool for Logstash's Grok parsing language.
Project-URL: Documentation, https://codeberg.org/spuzkov/dispozitsi#readme
Project-URL: Issues, https://codeberg.org/spuzkov/dispozitsi/issues
Project-URL: Source, https://codeberg.org/spuzkov/dispozitsi
Author-email: spuzkov <spuzkov@noreply.codeberg.org>
License-Expression: GPL-3.0-or-later
License-File: LICENSE
Keywords: Debugger,Grok,TUI,Textualize
Classifier: Development Status :: 4 - Beta
Classifier: Environment :: Console
Classifier: Programming Language :: Python
Classifier: Programming Language :: Python :: 3.8
Classifier: Programming Language :: Python :: 3.9
Classifier: Programming Language :: Python :: 3.10
Classifier: Programming Language :: Python :: 3.11
Classifier: Programming Language :: Python :: 3.12
Classifier: Programming Language :: Python :: Implementation :: CPython
Classifier: Programming Language :: Python :: Implementation :: PyPy
Requires-Python: >=3.11
Requires-Dist: textual-dev==1.7.0
Requires-Dist: textual[syntax]==5.2.0
